{
  "nodes": [
    {
      "id": "license_shopify_license",
      "label": "Shopify Dawn License",
      "file_type": "document",
      "source_file": "LICENSE.md",
      "source_location": null,
      "source_url": null,
      "captured_at": null,
      "author": "Shopify Inc.",
      "contributor": null
    },
    {
      "id": "readme_dawn_theme",
      "label": "Dawn Theme",
      "file_type": "document",
      "source_file": "README.md",
      "source_location": null,
      "source_url": "https://github.com/Shopify/dawn",
      "captured_at": null,
      "author": "Shopify Inc.",
      "contributor": null
    },
    {
      "id": "readme_html_first_approach",
      "label": "HTML-First JavaScript-Only-As-Needed Approach",
      "file_type": "rationale",
      "source_file": "README.md",
      "source_location": "line 14",
      "source_url": null,
      "captured_at": null,
      "author": null,
      "contributor": null
    },
    {
      "id": "readme_online_store_2",
      "label": "Online Store 2.0",
      "file_type": "rationale",
      "source_file": "README.md",
      "source_location": "line 14",
      "source_url": "https://www.shopify.com/partners/blog/shopify-online-store",
      "captured_at": null,
      "author": null,
      "contributor": null
    },
    {
      "id": "readme_progressive_enhancement",
      "label": "Progressive Enhancement",
      "file_type": "rationale",
      "source_file": "README.md",
      "source_location": "line 16",
      "source_url": null,
      "captured_at": null,
      "author": null,
      "contributor": null
    },
    {
      "id": "readme_server_rendered",
      "label": "Server-Rendered with Liquid",
      "file_type": "rationale",
      "source_file": "README.md",
      "source_location": "line 18",
      "source_url": null,
      "captured_at": null,
      "author": null,
      "contributor": null
    },
    {
      "id": "readme_shopify_cli",
      "label": "Shopify CLI",
      "file_type": "document",
      "source_file": "README.md",
      "source_location": "line 53-57",
      "source_url": "https://github.com/Shopify/shopify-cli",
      "captured_at": null,
      "author": null,
      "contributor": null
    },
    {
      "id": "readme_theme_check",
      "label": "Theme Check",
      "file_type": "document",
      "source_file": "README.md",
      "source_location": "line 59-68",
      "source_url": "https://github.com/shopify/theme-check",
      "captured_at": null,
      "author": null,
      "contributor": null
    },
    {
      "id": "readme_github_actions",
      "label": "GitHub Actions CI",
      "file_type": "document",
      "source_file": "README.md",
      "source_location": "line 71-73",
      "source_url": "https://github.com/features/actions",
      "captured_at": null,
      "author": null,
      "contributor": null
    },
    {
      "id": "readme_lighthouse_ci_action",
      "label": "Shopify Lighthouse CI Action",
      "file_type": "document",
      "source_file": "README.md",
      "source_location": "line 75-77",
      "source_url": "https://github.com/Shopify/lighthouse-ci-action",
      "captured_at": null,
      "author": null,
      "contributor": null
    },
    {
      "id": "readme_theme_check_action",
      "label": "Shopify Theme Check Action",
      "file_type": "document",
      "source_file": "README.md",
      "source_location": "line 79-81",
      "source_url": "https://github.com/Shopify/theme-check-action",
      "captured_at": null,
      "author": null,
      "contributor": null
    },
    {
      "id": "readme_theme_store",
      "label": "Shopify Theme Store",
      "file_type": "document",
      "source_file": "README.md",
      "source_location": "line 91-95",
      "source_url": "https://themes.shopify.com/",
      "captured_at": null,
      "author": null,
      "contributor": null
    },
    {
      "id": "readme_contributing_guide",
      "label": "Contributing Guide",
      "file_type": "document",
      "source_file": "README.md",
      "source_location": "line 83-85",
      "source_url": "https://github.com/Shopify/dawn/blob/main/.github/CONTRIBUTING.md",
      "captured_at": null,
      "author": null,
      "contributor": null
    },
    {
      "id": "releasenotes_dawn_1541",
      "label": "Dawn v15.4.1 Release Notes",
      "file_type": "document",
      "source_file": "release-notes.md",
      "source_location": "line 1",
      "source_url": null,
      "captured_at": null,
      "author": null,
      "contributor": null
    },
    {
      "id": "releasenotes_performance_monitoring",
      "label": "Performance Monitoring Improvements",
      "file_type": "rationale",
      "source_file": "release-notes.md",
      "source_location": "line 1",
      "source_url": null,
      "captured_at": null,
      "author": null,
      "contributor": null
    },
    {
      "id": "translation_config",
      "label": "Translation Configuration",
      "file_type": "document",
      "source_file": "translation.yml",
      "source_location": null,
      "source_url": null,
      "captured_at": null,
      "author": null,
      "contributor": null
    },
    {
      "id": "translation_buyer_component",
      "label": "Buyer Translation Component",
      "file_type": "document",
      "source_file": "translation.yml",
      "source_location": "line 7-12",
      "source_url": null,
      "captured_at": null,
      "author": null,
      "contributor": null
    },
    {
      "id": "translation_merchant_component",
      "label": "Merchant Translation Component",
      "file_type": "document",
      "source_file": "translation.yml",
      "source_location": "line 13-19",
      "source_url": null,
      "captured_at": null,
      "author": null,
      "contributor": null
    },
    {
      "id": "translation_themes_translations_team",
      "label": "Shopify Themes Translations Team",
      "file_type": "document",
      "source_file": "translation.yml",
      "source_location": "line 11,18",
      "source_url": null,
      "captured_at": null,
      "author": "@Shopify/themes-translations",
      "contributor": null
    },
    {
      "id": "email_signup_banner_background_mobile_bg",
      "label": "Email Signup Banner Background (Mobile)",
      "file_type": "image",
      "source_file": "assets/email-signup-banner-background-mobile.svg",
      "source_location": null,
      "source_url": null,
      "captured_at": null,
      "author": null,
      "contributor": null
    },
    {
      "id": "email_signup_banner_background_bg",
      "label": "Email Signup Banner Background (Desktop)",
      "file_type": "image",
      "source_file": "assets/email-signup-banner-background.svg",
      "source_location": null,
      "source_url": null,
      "captured_at": null,
      "author": null,
      "contributor": null
    },
    {
      "id": "icon_3d_model_icon",
      "label": "Icon: 3D Model",
      "file_type": "image",
      "source_file": "assets/icon-3d-model.svg",
      "source_location": null,
      "source_url": null,
      "captured_at": null,
      "author": null,
      "contributor": null
    },
    {
      "id": "icon_account_icon",
      "label": "Icon: Account (User Profile)",
      "file_type": "image",
      "source_file": "assets/icon-account.svg",
      "source_location": null,
      "source_url": null,
      "captured_at": null,
      "author": null,
      "contributor": null
    },
    {
      "id": "icon_apple_icon",
      "label": "Icon: Apple (Fruit)",
      "file_type": "image",
      "source_file": "assets/icon-apple.svg",
      "source_location": null,
      "source_url": null,
      "captured_at": null,
      "author": null,
      "contributor": null
    },
    {
      "id": "icon_arrow_icon",
      "label": "Icon: Arrow (Right-pointing)",
      "file_type": "image",
      "source_file": "assets/icon-arrow.svg",
      "source_location": null,
      "source_url": null,
      "captured_at": null,
      "author": null,
      "contributor": null
    },
    {
      "id": "icon_banana_icon",
      "label": "Icon: Banana (Fruit)",
      "file_type": "image",
      "source_file": "assets/icon-banana.svg",
      "source_location": null,
      "source_url": null,
      "captured_at": null,
      "author": null,
      "contributor": null
    },
    {
      "id": "icon_bottle_icon",
      "label": "Icon: Bottle (Supplement Container)",
      "file_type": "image",
      "source_file": "assets/icon-bottle.svg",
      "source_location": null,
      "source_url": null,
      "captured_at": null,
      "author": null,
      "contributor": null
    },
    {
      "id": "icon_box_icon",
      "label": "Icon: Box (3D Package)",
      "file_type": "image",
      "source_file": "assets/icon-box.svg",
      "source_location": null,
      "source_url": null,
      "captured_at": null,
      "author": null,
      "contributor": null
    },
    {
      "id": "icon_caret_icon",
      "label": "Icon: Caret (Dropdown Chevron)",
      "file_type": "image",
      "source_file": "assets/icon-caret.svg",
      "source_location": null,
      "source_url": null,
      "captured_at": null,
      "author": null,
      "contributor": null
    },
    {
      "id": "icon_carrot_icon",
      "label": "Icon: Carrot (Vegetable)",
      "file_type": "image",
      "source_file": "assets/icon-carrot.svg",
      "source_location": null,
      "source_url": null,
      "captured_at": null,
      "author": null,
      "contributor": null
    },
    {
      "id": "icon_cart_empty_icon",
      "label": "Icon: Cart Empty",
      "file_type": "image",
      "source_file": "assets/icon-cart-empty.svg",
      "source_location": null,
      "source_url": null,
      "captured_at": null,
      "author": null,
      "contributor": null
    },
    {
      "id": "icon_cart_icon",
      "label": "Icon: Cart (Shopping Bag)",
      "file_type": "image",
      "source_file": "assets/icon-cart.svg",
      "source_location": null,
      "source_url": null,
      "captured_at": null,
      "author": null,
      "contributor": null
    },
    {
      "id": "icon_chat_bubble_icon",
      "label": "Icon: Chat Bubble (Message/Support)",
      "file_type": "image",
      "source_file": "assets/icon-chat-bubble.svg",
      "source_location": null,
      "source_url": null,
      "captured_at": null,
      "author": null,
      "contributor": null
    },
    {
      "id": "icon_check_mark_icon",
      "label": "Icon: Check Mark (Checkbox with Border)",
      "file_type": "image",
      "source_file": "assets/icon-check-mark.svg",
      "source_location": null,
      "source_url": null,
      "captured_at": null,
      "author": null,
      "contributor": null
    },
    {
      "id": "icon_checkmark_icon",
      "label": "Icon: Checkmark (Simple Tick)",
      "file_type": "image",
      "source_file": "assets/icon-checkmark.svg",
      "source_location": null,
      "source_url": null,
      "captured_at": null,
      "author": null,
      "contributor": null
    },
    {
      "id": "icon_clipboard_icon",
      "label": "Icon: Clipboard (Notes/List)",
      "file_type": "image",
      "source_file": "assets/icon-clipboard.svg",
      "source_location": null,
      "source_url": null,
      "captured_at": null,
      "author": null,
      "contributor": null
    },
    {
      "id": "icon_close_small_icon",
      "label": "Icon: Close Small (X Dismiss)",
      "file_type": "image",
      "source_file": "assets/icon-close-small.svg",
      "source_location": null,
      "source_url": null,
      "captured_at": null,
      "author": null,
      "contributor": null
    },
    {
      "id": "icon_close_icon",
      "label": "Icon: Close (X Dismiss Large)",
      "file_type": "image",
      "source_file": "assets/icon-close.svg",
      "source_location": null,
      "source_url": null,
      "captured_at": null,
      "author": null,
      "contributor": null
    },
    {
      "id": "icon_copy_icon",
      "label": "Icon: Copy (Duplicate Document)",
      "file_type": "image",
      "source_file": "assets/icon-copy.svg",
      "source_location": null,
      "source_url": null,
      "captured_at": null,
      "author": null,
      "contributor": null
    },
    {
      "id": "icon_dairy_free_icon",
      "label": "Icon: Dairy Free (Badge/Dietary Label)",
      "file_type": "image",
      "source_file": "assets/icon-dairy-free.svg",
      "source_location": null,
      "source_url": null,
      "captured_at": null,
      "author": null,
      "contributor": null
    },
    {
      "id": "icon_dairy_icon",
      "label": "Icon: Dairy (Milk Jug/Bottle Badge)",
      "file_type": "image",
      "source_file": "assets/icon-dairy.svg",
      "source_location": null,
      "source_url": null,
      "captured_at": null,
      "author": null,
      "contributor": null
    },
    {
      "id": "icon-discount_discount",
      "label": "Discount / Price Tag Icon",
      "file_type": "image",
      "source_file": "assets/icon-discount.svg",
      "source_location": null,
      "source_url": null,
      "captured_at": null,
      "author": null,
      "contributor": null
    },
    {
      "id": "icon-dryer_dryer",
      "label": "Dryer / Laundry Care Icon",
      "file_type": "image",
      "source_file": "assets/icon-dryer.svg",
      "source_location": null,
      "source_url": null,
      "captured_at": null,
      "author": null,
      "contributor": null
    },
    {
      "id": "icon-error_error",
      "label": "Error / Alert Status Icon",
      "file_type": "image",
      "source_file": "assets/icon-error.svg",
      "source_location": null,
      "source_url": null,
      "captured_at": null,
      "author": null,
      "contributor": null
    },
    {
      "id": "icon-eye_eye",
      "label": "Eye / Visibility Icon",
      "file_type": "image",
      "source_file": "assets/icon-eye.svg",
      "source_location": null,
      "source_url": null,
      "captured_at": null,
      "author": null,
      "contributor": null
    },
    {
      "id": "icon-facebook_facebook",
      "label": "Facebook Social Media Icon",
      "file_type": "image",
      "source_file": "assets/icon-facebook.svg",
      "source_location": null,
      "source_url": null,
      "captured_at": null,
      "author": null,
      "contributor": null
    },
    {
      "id": "icon-filter_filter",
      "label": "Filter / Sort Controls Icon",
      "file_type": "image",
      "source_file": "assets/icon-filter.svg",
      "source_location": null,
      "source_url": null,
      "captured_at": null,
      "author": null,
      "contributor": null
    },
    {
      "id": "icon-fire_fire",
      "label": "Fire / Trending / Hot Icon",
      "file_type": "image",
      "source_file": "assets/icon-fire.svg",
      "source_location": null,
      "source_url": null,
      "captured_at": null,
      "author": null,
      "contributor": null
    },
    {
      "id": "icon-gluten-free_gluten_free",
      "label": "Gluten-Free Dietary Badge Icon",
      "file_type": "image",
      "source_file": "assets/icon-gluten-free.svg",
      "source_location": null,
      "source_url": null,
      "captured_at": null,
      "author": null,
      "contributor": null
    },
    {
      "id": "icon-hamburger_hamburger",
      "label": "Hamburger / Navigation Menu Icon",
      "file_type": "image",
      "source_file": "assets/icon-hamburger.svg",
      "source_location": null,
      "source_url": null,
      "captured_at": null,
      "author": null,
      "contributor": null
    },
    {
      "id": "icon-heart_heart",
      "label": "Heart / Wishlist / Favourite Icon",
      "file_type": "image",
      "source_file": "assets/icon-heart.svg",
      "source_location": null,
      "source_url": null,
      "captured_at": null,
      "author": null,
      "contributor": null
    },
    {
      "id": "icon-info_info",
      "label": "Info / Tooltip Icon",
      "file_type": "image",
      "source_file": "assets/icon-info.svg",
      "source_location": null,
      "source_url": null,
      "captured_at": null,
      "author": null,
      "contributor": null
    },
    {
      "id": "icon-instagram_instagram",
      "label": "Instagram Social Media Icon",
      "file_type": "image",
      "source_file": "assets/icon-instagram.svg",
      "source_location": null,
      "source_url": null,
      "captured_at": null,
      "author": null,
      "contributor": null
    },
    {
      "id": "icon-inventory-status_inventory_status",
      "label": "Inventory / Stock Status Indicator Icon",
      "file_type": "image",
      "source_file": "assets/icon-inventory-status.svg",
      "source_location": null,
      "source_url": null,
      "captured_at": null,
      "author": null,
      "contributor": null
    },
    {
      "id": "icon-iron_iron",
      "label": "Iron / Laundry Care Icon",
      "file_type": "image",
      "source_file": "assets/icon-iron.svg",
      "source_location": null,
      "source_url": null,
      "captured_at": null,
      "author": null,
      "contributor": null
    },
    {
      "id": "icon-leaf_leaf",
      "label": "Leaf / Natural / Organic Icon",
      "file_type": "image",
      "source_file": "assets/icon-leaf.svg",
      "source_location": null,
      "source_url": null,
      "captured_at": null,
      "author": null,
      "contributor": null
    },
    {
      "id": "icon-leather_leather",
      "label": "Leather / Material Care Icon",
      "file_type": "image",
      "source_file": "assets/icon-leather.svg",
      "source_location": null,
      "source_url": null,
      "captured_at": null,
      "author": null,
      "contributor": null
    },
    {
      "id": "icon-lightning-bolt_lightning_bolt",
      "label": "Lightning Bolt / Energy / Speed Icon",
      "file_type": "image",
      "source_file": "assets/icon-lightning-bolt.svg",
      "source_location": null,
      "source_url": null,
      "captured_at": null,
      "author": null,
      "contributor": null
    },
    {
      "id": "icon-lipstick_lipstick",
      "label": "Lipstick / Beauty Product Icon",
      "file_type": "image",
      "source_file": "assets/icon-lipstick.svg",
      "source_location": null,
      "source_url": null,
      "captured_at": null,
      "author": null,
      "contributor": null
    },
    {
      "id": "icon-lock_lock",
      "label": "Lock / Secure Checkout Icon",
      "file_type": "image",
      "source_file": "assets/icon-lock.svg",
      "source_location": null,
      "source_url": null,
      "captured_at": null,
      "author": null,
      "contributor": null
    },
    {
      "id": "icon-map-pin_map_pin",
      "label": "Map Pin / Location Icon",
      "file_type": "image",
      "source_file": "assets/icon-map-pin.svg",
      "source_location": null,
      "source_url": null,
      "captured_at": null,
      "author": null,
      "contributor": null
    },
    {
      "id": "icon-minus_minus",
      "label": "Minus / Decrease Quantity Icon",
      "file_type": "image",
      "source_file": "assets/icon-minus.svg",
      "source_location": null,
      "source_url": null,
      "captured_at": null,
      "author": null,
      "contributor": null
    },
    {
      "id": "icon-nut-free_nut_free",
      "label": "Nut-Free Dietary Badge Icon",
      "file_type": "image",
      "source_file": "assets/icon-nut-free.svg",
      "source_location": null,
      "source_url": null,
      "captured_at": null,
      "author": null,
      "contributor": null
    },
    {
      "id": "category_dietary_icons",
      "label": "Dietary / Allergen Claim Icons",
      "file_type": "image",
      "source_file": null,
      "source_location": null,
      "source_url": null,
      "captured_at": null,
      "author": null,
      "contributor": null
    },
    {
      "id": "category_social_media_icons",
      "label": "Social Media Share Icons",
      "file_type": "image",
      "source_file": null,
      "source_location": null,
      "source_url": null,
      "captured_at": null,
      "author": null,
      "contributor": null
    },
    {
      "id": "category_ui_status_icons",
      "label": "UI Status / Feedback Icons",
      "file_type": "image",
      "source_file": null,
      "source_location": null,
      "source_url": null,
      "captured_at": null,
      "author": null,
      "contributor": null
    },
    {
      "id": "category_navigation_icons",
      "label": "UI Navigation Icons",
      "file_type": "image",
      "source_file": null,
      "source_location": null,
      "source_url": null,
      "captured_at": null,
      "author": null,
      "contributor": null
    },
    {
      "id": "category_product_marketing_icons",
      "label": "Product / Marketing Claim Icons",
      "file_type": "image",
      "source_file": null,
      "source_location": null,
      "source_url": null,
      "captured_at": null,
      "author": null,
      "contributor": null
    },
    {
      "id": "category_laundry_care_icons",
      "label": "Laundry / Material Care Icons",
      "file_type": "image",
      "source_file": null,
      "source_location": null,
      "source_url": null,
      "captured_at": null,
      "author": null,
      "contributor": null
    },
    {
      "id": "category_ecommerce_action_icons",
      "label": "E-commerce Action / Interaction Icons",
      "file_type": "image",
      "source_file": null,
      "source_location": null,
      "source_url": null,
      "captured_at": null,
      "author": null,
      "contributor": null
    },
    {
      "id": "icon-padlock_security",
      "label": "Padlock Icon",
      "file_type": "image",
      "source_file": "assets/icon-padlock.svg",
      "source_location": null,
      "source_url": null,
      "captured_at": null,
      "author": null,
      "contributor": null
    },
    {
      "id": "icon-pants_apparel",
      "label": "Pants Icon",
      "file_type": "image",
      "source_file": "assets/icon-pants.svg",
      "source_location": null,
      "source_url": null,
      "captured_at": null,
      "author": null,
      "contributor": null
    },
    {
      "id": "icon-pause_media",
      "label": "Pause Icon",
      "file_type": "image",
      "source_file": "assets/icon-pause.svg",
      "source_location": null,
      "source_url": null,
      "captured_at": null,
      "author": null,
      "contributor": null
    },
    {
      "id": "icon-paw-print_pet",
      "label": "Paw Print Icon",
      "file_type": "image",
      "source_file": "assets/icon-paw-print.svg",
      "source_location": null,
      "source_url": null,
      "captured_at": null,
      "author": null,
      "contributor": null
    },
    {
      "id": "icon-pepper_food",
      "label": "Pepper Icon",
      "file_type": "image",
      "source_file": "assets/icon-pepper.svg",
      "source_location": null,
      "source_url": null,
      "captured_at": null,
      "author": null,
      "contributor": null
    },
    {
      "id": "icon-perfume_beauty",
      "label": "Perfume Bottle Icon",
      "file_type": "image",
      "source_file": "assets/icon-perfume.svg",
      "source_location": null,
      "source_url": null,
      "captured_at": null,
      "author": null,
      "contributor": null
    },
    {
      "id": "icon-pinterest_social",
      "label": "Pinterest Icon",
      "file_type": "image",
      "source_file": "assets/icon-pinterest.svg",
      "source_location": null,
      "source_url": null,
      "captured_at": null,
      "author": null,
      "contributor": null
    },
    {
      "id": "icon-plane_shipping",
      "label": "Airplane / Shipping Icon",
      "file_type": "image",
      "source_file": "assets/icon-plane.svg",
      "source_location": null,
      "source_url": null,
      "captured_at": null,
      "author": null,
      "contributor": null
    },
    {
      "id": "icon-plant_nature",
      "label": "Plant / Leaf Icon",
      "file_type": "image",
      "source_file": "assets/icon-plant.svg",
      "source_location": null,
      "source_url": null,
      "captured_at": null,
      "author": null,
      "contributor": null
    },
    {
      "id": "icon-play_media",
      "label": "Play Button Icon",
      "file_type": "image",
      "source_file": "assets/icon-play.svg",
      "source_location": null,
      "source_url": null,
      "captured_at": null,
      "author": null,
      "contributor": null
    },
    {
      "id": "icon-plus_ui",
      "label": "Plus / Add Icon",
      "file_type": "image",
      "source_file": "assets/icon-plus.svg",
      "source_location": null,
      "source_url": null,
      "captured_at": null,
      "author": null,
      "contributor": null
    },
    {
      "id": "icon-price-tag_ecommerce",
      "label": "Price Tag Icon",
      "file_type": "image",
      "source_file": "assets/icon-price-tag.svg",
      "source_location": null,
      "source_url": null,
      "captured_at": null,
      "author": null,
      "contributor": null
    },
    {
      "id": "icon-question-mark_ui",
      "label": "Question Mark / Help Icon",
      "file_type": "image",
      "source_file": "assets/icon-question-mark.svg",
      "source_location": null,
      "source_url": null,
      "captured_at": null,
      "author": null,
      "contributor": null
    },
    {
      "id": "icon-recycle_sustainability",
      "label": "Recycle Icon",
      "file_type": "image",
      "source_file": "assets/icon-recycle.svg",
      "source_location": null,
      "source_url": null,
      "captured_at": null,
      "author": null,
      "contributor": null
    },
    {
      "id": "icon-remove_ui",
      "label": "Remove / Trash Icon",
      "file_type": "image",
      "source_file": "assets/icon-remove.svg",
      "source_location": null,
      "source_url": null,
      "captured_at": null,
      "author": null,
      "contributor": null
    },
    {
      "id": "icon-reset_ui",
      "label": "Reset / Close Icon",
      "file_type": "image",
      "source_file": "assets/icon-reset.svg",
      "source_location": null,
      "source_url": null,
      "captured_at": null,
      "author": null,
      "contributor": null
    },
    {
      "id": "icon-return_ecommerce",
      "label": "Return / Back Arrow Icon",
      "file_type": "image",
      "source_file": "assets/icon-return.svg",
      "source_location": null,
      "source_url": null,
      "captured_at": null,
      "author": null,
      "contributor": null
    },
    {
      "id": "icon-ruler_sizing",
      "label": "Ruler / Measurement Icon",
      "file_type": "image",
      "source_file": "assets/icon-ruler.svg",
      "source_location": null,
      "source_url": null,
      "captured_at": null,
      "author": null,
      "contributor": null
    },
    {
      "id": "icon-search_ui",
      "label": "Search / Magnifier Icon",
      "file_type": "image",
      "source_file": "assets/icon-search.svg",
      "source_location": null,
      "source_url": null,
      "captured_at": null,
      "author": null,
      "contributor": null
    },
    {
      "id": "icon-serving-dish_food",
      "label": "Serving Dish / Cloche Icon",
      "file_type": "image",
      "source_file": "assets/icon-serving-dish.svg",
      "source_location": null,
      "source_url": null,
      "captured_at": null,
      "author": null,
      "contributor": null
    },
    {
      "id": "icon-share_social",
      "label": "Share Icon",
      "file_type": "image",
      "source_file": "assets/icon-share.svg",
      "source_location": null,
      "source_url": null,
      "captured_at": null,
      "author": null,
      "contributor": null
    },
    {
      "id": "icon-shirt_apparel",
      "label": "Shirt / T-Shirt Icon",
      "file_type": "image",
      "source_file": "assets/icon-shirt.svg",
      "source_location": null,
      "source_url": null,
      "captured_at": null,
      "author": null,
      "contributor": null
    },
    {
      "id": "icon_shoe",
      "label": "Shoe Icon",
      "file_type": "image/svg+xml",
      "source_file": "assets/icon-shoe.svg",
      "source_location": null,
      "source_url": null,
      "captured_at": null,
      "author": null,
      "contributor": null
    },
    {
      "id": "icon_shopify",
      "label": "Shopify Logo Icon",
      "file_type": "image/svg+xml",
      "source_file": "assets/icon-shopify.svg",
      "source_location": null,
      "source_url": null,
      "captured_at": null,
      "author": null,
      "contributor": null
    },
    {
      "id": "icon_silhouette",
      "label": "Person Silhouette / User Account Icon",
      "file_type": "image/svg+xml",
      "source_file": "assets/icon-silhouette.svg",
      "source_location": null,
      "source_url": null,
      "captured_at": null,
      "author": null,
      "contributor": null
    },
    {
      "id": "icon_snapchat",
      "label": "Snapchat Social Media Icon",
      "file_type": "image/svg+xml",
      "source_file": "assets/icon-snapchat.svg",
      "source_location": null,
      "source_url": null,
      "captured_at": null,
      "author": null,
      "contributor": null
    },
    {
      "id": "icon_snowflake",
      "label": "Snowflake / Cold Storage Icon",
      "file_type": "image/svg+xml",
      "source_file": "assets/icon-snowflake.svg",
      "source_location": null,
      "source_url": null,
      "captured_at": null,
      "author": null,
      "contributor": null
    },
    {
      "id": "icon_star",
      "label": "Star / Rating Icon",
      "file_type": "image/svg+xml",
      "source_file": "assets/icon-star.svg",
      "source_location": null,
      "source_url": null,
      "captured_at": null,
      "author": null,
      "contributor": null
    },
    {
      "id": "icon_stopwatch",
      "label": "Stopwatch / Timer Icon",
      "file_type": "image/svg+xml",
      "source_file": "assets/icon-stopwatch.svg",
      "source_location": null,
      "source_url": null,
      "captured_at": null,
      "author": null,
      "contributor": null
    },
    {
      "id": "icon_success",
      "label": "Success / Confirmation Circle Icon",
      "file_type": "image/svg+xml",
      "source_file": "assets/icon-success.svg",
      "source_location": null,
      "source_url": null,
      "captured_at": null,
      "author": null,
      "contributor": null
    },
    {
      "id": "icon_tick",
      "label": "Tick / Checkmark Icon",
      "file_type": "image/svg+xml",
      "source_file": "assets/icon-tick.svg",
      "source_location": null,
      "source_url": null,
      "captured_at": null,
      "author": null,
      "contributor": null
    },
    {
      "id": "icon_tiktok",
      "label": "TikTok Social Media Icon",
      "file_type": "image/svg+xml",
      "source_file": "assets/icon-tiktok.svg",
      "source_location": null,
      "source_url": null,
      "captured_at": null,
      "author": null,
      "contributor": null
    },
    {
      "id": "icon_truck",
      "label": "Delivery Truck / Shipping Icon",
      "file_type": "image/svg+xml",
      "source_file": "assets/icon-truck.svg",
      "source_location": null,
      "source_url": null,
      "captured_at": null,
      "author": null,
      "contributor": null
    },
    {
      "id": "icon_tumblr",
      "label": "Tumblr Social Media Icon",
      "file_type": "image/svg+xml",
      "source_file": "assets/icon-tumblr.svg",
      "source_location": null,
      "source_url": null,
      "captured_at": null,
      "author": null,
      "contributor": null
    },
    {
      "id": "icon_twitter",
      "label": "Twitter / X Social Media Icon",
      "file_type": "image/svg+xml",
      "source_file": "assets/icon-twitter.svg",
      "source_location": null,
      "source_url": null,
      "captured_at": null,
      "author": null,
      "contributor": null
    },
    {
      "id": "icon_unavailable",
      "label": "Unavailable / Error X Icon",
      "file_type": "image/svg+xml",
      "source_file": "assets/icon-unavailable.svg",
      "source_location": null,
      "source_url": null,
      "captured_at": null,
      "author": null,
      "contributor": null
    },
    {
      "id": "icon_vimeo",
      "label": "Vimeo Social Media Icon",
      "file_type": "image/svg+xml",
      "source_file": "assets/icon-vimeo.svg",
      "source_location": null,
      "source_url": null,
      "captured_at": null,
      "author": null,
      "contributor": null
    },
    {
      "id": "icon_washing",
      "label": "Washing / Care Instructions Icon",
      "file_type": "image/svg+xml",
      "source_file": "assets/icon-washing.svg",
      "source_location": null,
      "source_url": null,
      "captured_at": null,
      "author": null,
      "contributor": null
    },
    {
      "id": "icon_youtube",
      "label": "YouTube Social Media Icon",
      "file_type": "image/svg+xml",
      "source_file": "assets/icon-youtube.svg",
      "source_location": null,
      "source_url": null,
      "captured_at": null,
      "author": null,
      "contributor": null
    },
    {
      "id": "icon_zoom",
      "label": "Zoom In / Magnify Search Icon",
      "file_type": "image/svg+xml",
      "source_file": "assets/icon-zoom.svg",
      "source_location": null,
      "source_url": null,
      "captured_at": null,
      "author": null,
      "contributor": null
    },
    {
      "id": "loading_spinner",
      "label": "Loading Spinner Animation",
      "file_type": "image/svg+xml",
      "source_file": "assets/loading-spinner.svg",
      "source_location": null,
      "source_url": null,
      "captured_at": null,
      "author": null,
      "contributor": null
    },
    {
      "id": "mask_arch",
      "label": "Arch Shape Clip Path Mask",
      "file_type": "image/svg+xml",
      "source_file": "assets/mask-arch.svg",
      "source_location": null,
      "source_url": null,
      "captured_at": null,
      "author": null,
      "contributor": null
    },
    {
      "id": "square",
      "label": "Square / Checkbox Outline Shape",
      "file_type": "image/svg+xml",
      "source_file": "assets/square.svg",
      "source_location": null,
      "source_url": null,
      "captured_at": null,
      "author": null,
      "contributor": null
    },
    {
      "id": "sparkle_gif",
      "label": "Sparkle Decorative Animation",
      "file_type": "image/gif",
      "source_file": "assets/sparkle.gif",
      "source_location": null,
      "source_url": null,
      "captured_at": null,
      "author": null,
      "contributor": null
    },
    {
      "id": "category_social_media_icons",
      "label": "Social Media Icons Group",
      "file_type": "concept",
      "source_file": null,
      "source_location": null,
      "source_url": null,
      "captured_at": null,
      "author": null,
      "contributor": null
    },
    {
      "id": "category_ui_feedback_icons",
      "label": "UI Feedback Icons Group",
      "file_type": "concept",
      "source_file": null,
      "source_location": null,
      "source_url": null,
      "captured_at": null,
      "author": null,
      "contributor": null
    },
    {
      "id": "category_ecommerce_icons",
      "label": "E-Commerce / Shopping Icons Group",
      "file_type": "concept",
      "source_file": null,
      "source_location": null,
      "source_url": null,
      "captured_at": null,
      "author": null,
      "contributor": null
    },
    {
      "id": "category_product_care_icons",
      "label": "Product / Care Instructions Icons Group",
      "file_type": "concept",
      "source_file": null,
      "source_location": null,
      "source_url": null,
      "captured_at": null,
      "author": null,
      "contributor": null
    },
    {
      "id": "category_ui_shapes",
      "label": "UI Shapes / Structural Elements Group",
      "file_type": "concept",
      "source_file": null,
      "source_location": null,
      "source_url": null,
      "captured_at": null,
      "author": null,
      "contributor": null
    },
    {
      "id": "category_platform_branding",
      "label": "Platform Branding Icons Group",
      "file_type": "concept",
      "source_file": null,
      "source_location": null,
      "source_url": null,
      "captured_at": null,
      "author": null,
      "contributor": null
    }
  ],
  "edges": [
    {
      "source": "readme_dawn_theme",
      "target": "license_shopify_license",
      "relation": "references",
      "confidence": "EXTRACTED",
      "confidence_score": 1.0,
      "source_file": "README.md",
      "source_location": "line 99",
      "weight": 1.0
    },
    {
      "source": "readme_dawn_theme",
      "target": "readme_contributing_guide",
      "relation": "references",
      "confidence": "EXTRACTED",
      "confidence_score": 1.0,
      "source_file": "README.md",
      "source_location": "line 21",
      "weight": 1.0
    },
    {
      "source": "readme_dawn_theme",
      "target": "readme_html_first_approach",
      "relation": "implements",
      "confidence": "EXTRACTED",
      "confidence_score": 1.0,
      "source_file": "README.md",
      "source_location": "line 14",
      "weight": 1.0
    },
    {
      "source": "readme_dawn_theme",
      "target": "readme_online_store_2",
      "relation": "implements",
      "confidence": "EXTRACTED",
      "confidence_score": 1.0,
      "source_file": "README.md",
      "source_location": "line 14",
      "weight": 1.0
    },
    {
      "source": "readme_dawn_theme",
      "target": "readme_progressive_enhancement",
      "relation": "implements",
      "confidence": "EXTRACTED",
      "confidence_score": 1.0,
      "source_file": "README.md",
      "source_location": "line 16",
      "weight": 1.0
    },
    {
      "source": "readme_dawn_theme",
      "target": "readme_server_rendered",
      "relation": "implements",
      "confidence": "EXTRACTED",
      "confidence_score": 1.0,
      "source_file": "README.md",
      "source_location": "line 18",
      "weight": 1.0
    },
    {
      "source": "readme_dawn_theme",
      "target": "readme_shopify_cli",
      "relation": "references",
      "confidence": "EXTRACTED",
      "confidence_score": 1.0,
      "source_file": "README.md",
      "source_location": "line 53",
      "weight": 1.0
    },
    {
      "source": "readme_dawn_theme",
      "target": "readme_theme_check",
      "relation": "references",
      "confidence": "EXTRACTED",
      "confidence_score": 1.0,
      "source_file": "README.md",
      "source_location": "line 59",
      "weight": 1.0
    },
    {
      "source": "readme_dawn_theme",
      "target": "readme_github_actions",
      "relation": "references",
      "confidence": "EXTRACTED",
      "confidence_score": 1.0,
      "source_file": "README.md",
      "source_location": "line 71",
      "weight": 1.0
    },
    {
      "source": "readme_dawn_theme",
      "target": "readme_lighthouse_ci_action",
      "relation": "references",
      "confidence": "EXTRACTED",
      "confidence_score": 1.0,
      "source_file": "README.md",
      "source_location": "line 75",
      "weight": 1.0
    },
    {
      "source": "readme_dawn_theme",
      "target": "readme_theme_check_action",
      "relation": "references",
      "confidence": "EXTRACTED",
      "confidence_score": 1.0,
      "source_file": "README.md",
      "source_location": "line 79",
      "weight": 1.0
    },
    {
      "source": "readme_dawn_theme",
      "target": "readme_theme_store",
      "relation": "references",
      "confidence": "EXTRACTED",
      "confidence_score": 1.0,
      "source_file": "README.md",
      "source_location": "line 91",
      "weight": 1.0
    },
    {
      "source": "readme_github_actions",
      "target": "readme_lighthouse_ci_action",
      "relation": "references",
      "confidence": "EXTRACTED",
      "confidence_score": 1.0,
      "source_file": "README.md",
      "source_location": "line 75",
      "weight": 1.0
    },
    {
      "source": "readme_github_actions",
      "target": "readme_theme_check_action",
      "relation": "references",
      "confidence": "EXTRACTED",
      "confidence_score": 1.0,
      "source_file": "README.md",
      "source_location": "line 79",
      "weight": 1.0
    },
    {
      "source": "releasenotes_dawn_1541",
      "target": "readme_dawn_theme",
      "relation": "references",
      "confidence": "EXTRACTED",
      "confidence_score": 1.0,
      "source_file": "release-notes.md",
      "source_location": "line 1",
      "weight": 1.0
    },
    {
      "source": "releasenotes_dawn_1541",
      "target": "releasenotes_performance_monitoring",
      "relation": "references",
      "confidence": "EXTRACTED",
      "confidence_score": 1.0,
      "source_file": "release-notes.md",
      "source_location": "line 1",
      "weight": 1.0
    },
    {
      "source": "releasenotes_performance_monitoring",
      "target": "readme_lighthouse_ci_action",
      "relation": "conceptually_related_to",
      "confidence": "INFERRED",
      "confidence_score": 0.75,
      "source_file": "release-notes.md",
      "source_location": "line 1",
      "weight": 0.75
    },
    {
      "source": "translation_config",
      "target": "readme_dawn_theme",
      "relation": "references",
      "confidence": "INFERRED",
      "confidence_score": 0.95,
      "source_file": "translation.yml",
      "source_location": null,
      "weight": 0.95
    },
    {
      "source": "translation_config",
      "target": "translation_buyer_component",
      "relation": "references",
      "confidence": "EXTRACTED",
      "confidence_score": 1.0,
      "source_file": "translation.yml",
      "source_location": "line 7-12",
      "weight": 1.0
    },
    {
      "source": "translation_config",
      "target": "translation_merchant_component",
      "relation": "references",
      "confidence": "EXTRACTED",
      "confidence_score": 1.0,
      "source_file": "translation.yml",
      "source_location": "line 13-19",
      "weight": 1.0
    },
    {
      "source": "translation_buyer_component",
      "target": "translation_themes_translations_team",
      "relation": "references",
      "confidence": "EXTRACTED",
      "confidence_score": 1.0,
      "source_file": "translation.yml",
      "source_location": "line 11",
      "weight": 1.0
    },
    {
      "source": "translation_merchant_component",
      "target": "translation_themes_translations_team",
      "relation": "references",
      "confidence": "EXTRACTED",
      "confidence_score": 1.0,
      "source_file": "translation.yml",
      "source_location": "line 18",
      "weight": 1.0
    },
    {
      "source": "readme_html_first_approach",
      "target": "readme_server_rendered",
      "relation": "semantically_similar_to",
      "confidence": "INFERRED",
      "confidence_score": 0.65,
      "source_file": "README.md",
      "source_location": "line 14-18",
      "weight": 0.65
    },
    {
      "source": "readme_theme_check",
      "target": "readme_theme_check_action",
      "relation": "implements",
      "confidence": "EXTRACTED",
      "confidence_score": 1.0,
      "source_file": "README.md",
      "source_location": "line 79-81",
      "weight": 1.0
    },
    {
      "source": "email_signup_banner_background_mobile_bg",
      "target": "email_signup_banner_background_bg",
      "relation": "semantically_similar_to",
      "confidence": "EXTRACTED",
      "confidence_score": 1.0,
      "source_file": "assets/email-signup-banner-background-mobile.svg",
      "source_location": null,
      "weight": 1.0
    },
    {
      "source": "icon_cart_empty_icon",
      "target": "icon_cart_icon",
      "relation": "semantically_similar_to",
      "confidence": "EXTRACTED",
      "confidence_score": 1.0,
      "source_file": "assets/icon-cart-empty.svg",
      "source_location": null,
      "weight": 1.0
    },
    {
      "source": "icon_check_mark_icon",
      "target": "icon_checkmark_icon",
      "relation": "semantically_similar_to",
      "confidence": "EXTRACTED",
      "confidence_score": 1.0,
      "source_file": "assets/icon-check-mark.svg",
      "source_location": null,
      "weight": 0.9
    },
    {
      "source": "icon_close_small_icon",
      "target": "icon_close_icon",
      "relation": "semantically_similar_to",
      "confidence": "EXTRACTED",
      "confidence_score": 1.0,
      "source_file": "assets/icon-close-small.svg",
      "source_location": null,
      "weight": 0.9
    },
    {
      "source": "icon_clipboard_icon",
      "target": "icon_copy_icon",
      "relation": "semantically_similar_to",
      "confidence": "INFERRED",
      "confidence_score": 0.75,
      "source_file": "assets/icon-clipboard.svg",
      "source_location": null,
      "weight": 0.75
    },
    {
      "source": "icon_dairy_free_icon",
      "target": "icon_dairy_icon",
      "relation": "semantically_similar_to",
      "confidence": "EXTRACTED",
      "confidence_score": 1.0,
      "source_file": "assets/icon-dairy-free.svg",
      "source_location": null,
      "weight": 1.0
    },
    {
      "source": "icon_apple_icon",
      "target": "icon_banana_icon",
      "relation": "semantically_similar_to",
      "confidence": "INFERRED",
      "confidence_score": 0.95,
      "source_file": "assets/icon-apple.svg",
      "source_location": null,
      "weight": 0.95
    },
    {
      "source": "icon_apple_icon",
      "target": "icon_carrot_icon",
      "relation": "semantically_similar_to",
      "confidence": "INFERRED",
      "confidence_score": 0.85,
      "source_file": "assets/icon-apple.svg",
      "source_location": null,
      "weight": 0.85
    },
    {
      "source": "icon_banana_icon",
      "target": "icon_carrot_icon",
      "relation": "semantically_similar_to",
      "confidence": "INFERRED",
      "confidence_score": 0.85,
      "source_file": "assets/icon-banana.svg",
      "source_location": null,
      "weight": 0.85
    },
    {
      "source": "icon_bottle_icon",
      "target": "icon_box_icon",
      "relation": "semantically_similar_to",
      "confidence": "INFERRED",
      "confidence_score": 0.75,
      "source_file": "assets/icon-bottle.svg",
      "source_location": null,
      "weight": 0.75
    },
    {
      "source": "icon_arrow_icon",
      "target": "icon_caret_icon",
      "relation": "semantically_similar_to",
      "confidence": "INFERRED",
      "confidence_score": 0.85,
      "source_file": "assets/icon-arrow.svg",
      "source_location": null,
      "weight": 0.85
    },
    {
      "source": "icon_bottle_icon",
      "target": "icon_dairy_icon",
      "relation": "conceptually_related_to",
      "confidence": "INFERRED",
      "confidence_score": 0.65,
      "source_file": "assets/icon-bottle.svg",
      "source_location": null,
      "weight": 0.65
    },
    {
      "source": "icon_apple_icon",
      "target": "icon_dairy_free_icon",
      "relation": "conceptually_related_to",
      "confidence": "INFERRED",
      "confidence_score": 0.65,
      "source_file": "assets/icon-apple.svg",
      "source_location": null,
      "weight": 0.65
    },
    {
      "source": "icon_3d_model_icon",
      "target": "icon_box_icon",
      "relation": "conceptually_related_to",
      "confidence": "INFERRED",
      "confidence_score": 0.55,
      "source_file": "assets/icon-3d-model.svg",
      "source_location": null,
      "weight": 0.55
    },
    {
      "source": "icon_cart_icon",
      "target": "icon_account_icon",
      "relation": "conceptually_related_to",
      "confidence": "INFERRED",
      "confidence_score": 0.75,
      "source_file": "assets/icon-cart.svg",
      "source_location": null,
      "weight": 0.75
    },
    {
      "source": "icon_chat_bubble_icon",
      "target": "icon_account_icon",
      "relation": "conceptually_related_to",
      "confidence": "INFERRED",
      "confidence_score": 0.65,
      "source_file": "assets/icon-chat-bubble.svg",
      "source_location": null,
      "weight": 0.65
    },
    {
      "source": "icon-gluten-free_gluten_free",
      "target": "category_dietary_icons",
      "relation": "conceptually_related_to",
      "confidence": "EXTRACTED",
      "confidence_score": 1.0,
      "source_file": "assets/icon-gluten-free.svg",
      "source_location": null,
      "weight": 1.0
    },
    {
      "source": "icon-nut-free_nut_free",
      "target": "category_dietary_icons",
      "relation": "conceptually_related_to",
      "confidence": "EXTRACTED",
      "confidence_score": 1.0,
      "source_file": "assets/icon-nut-free.svg",
      "source_location": null,
      "weight": 1.0
    },
    {
      "source": "icon-gluten-free_gluten_free",
      "target": "icon-nut-free_nut_free",
      "relation": "semantically_similar_to",
      "confidence": "INFERRED",
      "confidence_score": 0.95,
      "source_file": "assets/icon-gluten-free.svg",
      "source_location": null,
      "weight": 0.95
    },
    {
      "source": "icon-facebook_facebook",
      "target": "category_social_media_icons",
      "relation": "conceptually_related_to",
      "confidence": "EXTRACTED",
      "confidence_score": 1.0,
      "source_file": "assets/icon-facebook.svg",
      "source_location": null,
      "weight": 1.0
    },
    {
      "source": "icon-instagram_instagram",
      "target": "category_social_media_icons",
      "relation": "conceptually_related_to",
      "confidence": "EXTRACTED",
      "confidence_score": 1.0,
      "source_file": "assets/icon-instagram.svg",
      "source_location": null,
      "weight": 1.0
    },
    {
      "source": "icon-facebook_facebook",
      "target": "icon-instagram_instagram",
      "relation": "semantically_similar_to",
      "confidence": "INFERRED",
      "confidence_score": 0.95,
      "source_file": "assets/icon-facebook.svg",
      "source_location": null,
      "weight": 0.95
    },
    {
      "source": "icon-error_error",
      "target": "category_ui_status_icons",
      "relation": "conceptually_related_to",
      "confidence": "EXTRACTED",
      "confidence_score": 1.0,
      "source_file": "assets/icon-error.svg",
      "source_location": null,
      "weight": 1.0
    },
    {
      "source": "icon-info_info",
      "target": "category_ui_status_icons",
      "relation": "conceptually_related_to",
      "confidence": "EXTRACTED",
      "confidence_score": 1.0,
      "source_file": "assets/icon-info.svg",
      "source_location": null,
      "weight": 1.0
    },
    {
      "source": "icon-inventory-status_inventory_status",
      "target": "category_ui_status_icons",
      "relation": "conceptually_related_to",
      "confidence": "EXTRACTED",
      "confidence_score": 1.0,
      "source_file": "assets/icon-inventory-status.svg",
      "source_location": null,
      "weight": 1.0
    },
    {
      "source": "icon-error_error",
      "target": "icon-info_info",
      "relation": "semantically_similar_to",
      "confidence": "INFERRED",
      "confidence_score": 0.85,
      "source_file": "assets/icon-error.svg",
      "source_location": null,
      "weight": 0.85
    },
    {
      "source": "icon-hamburger_hamburger",
      "target": "category_navigation_icons",
      "relation": "conceptually_related_to",
      "confidence": "EXTRACTED",
      "confidence_score": 1.0,
      "source_file": "assets/icon-hamburger.svg",
      "source_location": null,
      "weight": 1.0
    },
    {
      "source": "icon-filter_filter",
      "target": "category_navigation_icons",
      "relation": "conceptually_related_to",
      "confidence": "INFERRED",
      "confidence_score": 0.85,
      "source_file": "assets/icon-filter.svg",
      "source_location": null,
      "weight": 0.85
    },
    {
      "source": "icon-map-pin_map_pin",
      "target": "category_navigation_icons",
      "relation": "conceptually_related_to",
      "confidence": "INFERRED",
      "confidence_score": 0.85,
      "source_file": "assets/icon-map-pin.svg",
      "source_location": null,
      "weight": 0.85
    },
    {
      "source": "icon-leaf_leaf",
      "target": "category_product_marketing_icons",
      "relation": "conceptually_related_to",
      "confidence": "INFERRED",
      "confidence_score": 0.95,
      "source_file": "assets/icon-leaf.svg",
      "source_location": null,
      "weight": 0.95
    },
    {
      "source": "icon-fire_fire",
      "target": "category_product_marketing_icons",
      "relation": "conceptually_related_to",
      "confidence": "INFERRED",
      "confidence_score": 0.85,
      "source_file": "assets/icon-fire.svg",
      "source_location": null,
      "weight": 0.85
    },
    {
      "source": "icon-lightning-bolt_lightning_bolt",
      "target": "category_product_marketing_icons",
      "relation": "conceptually_related_to",
      "confidence": "INFERRED",
      "confidence_score": 0.85,
      "source_file": "assets/icon-lightning-bolt.svg",
      "source_location": null,
      "weight": 0.85
    },
    {
      "source": "icon-discount_discount",
      "target": "category_product_marketing_icons",
      "relation": "conceptually_related_to",
      "confidence": "INFERRED",
      "confidence_score": 0.95,
      "source_file": "assets/icon-discount.svg",
      "source_location": null,
      "weight": 0.95
    },
    {
      "source": "icon-leaf_leaf",
      "target": "icon-fire_fire",
      "relation": "semantically_similar_to",
      "confidence": "INFERRED",
      "confidence_score": 0.65,
      "source_file": "assets/icon-leaf.svg",
      "source_location": null,
      "weight": 0.65
    },
    {
      "source": "icon-fire_fire",
      "target": "icon-lightning-bolt_lightning_bolt",
      "relation": "semantically_similar_to",
      "confidence": "INFERRED",
      "confidence_score": 0.75,
      "source_file": "assets/icon-fire.svg",
      "source_location": null,
      "weight": 0.75
    },
    {
      "source": "icon-dryer_dryer",
      "target": "category_laundry_care_icons",
      "relation": "conceptually_related_to",
      "confidence": "EXTRACTED",
      "confidence_score": 1.0,
      "source_file": "assets/icon-dryer.svg",
      "source_location": null,
      "weight": 1.0
    },
    {
      "source": "icon-iron_iron",
      "target": "category_laundry_care_icons",
      "relation": "conceptually_related_to",
      "confidence": "EXTRACTED",
      "confidence_score": 1.0,
      "source_file": "assets/icon-iron.svg",
      "source_location": null,
      "weight": 1.0
    },
    {
      "source": "icon-leather_leather",
      "target": "category_laundry_care_icons",
      "relation": "conceptually_related_to",
      "confidence": "INFERRED",
      "confidence_score": 0.75,
      "source_file": "assets/icon-leather.svg",
      "source_location": null,
      "weight": 0.75
    },
    {
      "source": "icon-dryer_dryer",
      "target": "icon-iron_iron",
      "relation": "semantically_similar_to",
      "confidence": "INFERRED",
      "confidence_score": 0.95,
      "source_file": "assets/icon-dryer.svg",
      "source_location": null,
      "weight": 0.95
    },
    {
      "source": "icon-heart_heart",
      "target": "category_ecommerce_action_icons",
      "relation": "conceptually_related_to",
      "confidence": "INFERRED",
      "confidence_score": 0.95,
      "source_file": "assets/icon-heart.svg",
      "source_location": null,
      "weight": 0.95
    },
    {
      "source": "icon-lock_lock",
      "target": "category_ecommerce_action_icons",
      "relation": "conceptually_related_to",
      "confidence": "INFERRED",
      "confidence_score": 0.95,
      "source_file": "assets/icon-lock.svg",
      "source_location": null,
      "weight": 0.95
    },
    {
      "source": "icon-minus_minus",
      "target": "category_ecommerce_action_icons",
      "relation": "conceptually_related_to",
      "confidence": "INFERRED",
      "confidence_score": 0.95,
      "source_file": "assets/icon-minus.svg",
      "source_location": null,
      "weight": 0.95
    },
    {
      "source": "icon-eye_eye",
      "target": "category_ecommerce_action_icons",
      "relation": "conceptually_related_to",
      "confidence": "INFERRED",
      "confidence_score": 0.85,
      "source_file": "assets/icon-eye.svg",
      "source_location": null,
      "weight": 0.85
    },
    {
      "source": "icon-lipstick_lipstick",
      "target": "category_product_marketing_icons",
      "relation": "conceptually_related_to",
      "confidence": "INFERRED",
      "confidence_score": 0.75,
      "source_file": "assets/icon-lipstick.svg",
      "source_location": null,
      "weight": 0.75
    },
    {
      "source": "icon-heart_heart",
      "target": "icon-lock_lock",
      "relation": "semantically_similar_to",
      "confidence": "INFERRED",
      "confidence_score": 0.55,
      "source_file": "assets/icon-heart.svg",
      "source_location": null,
      "weight": 0.55
    },
    {
      "source": "icon-discount_discount",
      "target": "icon-heart_heart",
      "relation": "conceptually_related_to",
      "confidence": "INFERRED",
      "confidence_score": 0.65,
      "source_file": "assets/icon-discount.svg",
      "source_location": null,
      "weight": 0.65
    },
    {
      "source": "icon-leaf_leaf",
      "target": "icon-gluten-free_gluten_free",
      "relation": "semantically_similar_to",
      "confidence": "INFERRED",
      "confidence_score": 0.75,
      "source_file": "assets/icon-leaf.svg",
      "source_location": null,
      "weight": 0.75
    },
    {
      "source": "icon-leaf_leaf",
      "target": "icon-nut-free_nut_free",
      "relation": "semantically_similar_to",
      "confidence": "INFERRED",
      "confidence_score": 0.75,
      "source_file": "assets/icon-leaf.svg",
      "source_location": null,
      "weight": 0.75
    },
    {
      "source": "icon-inventory-status_inventory_status",
      "target": "icon-error_error",
      "relation": "semantically_similar_to",
      "confidence": "INFERRED",
      "confidence_score": 0.65,
      "source_file": "assets/icon-inventory-status.svg",
      "source_location": null,
      "weight": 0.65
    },
    {
      "source": "icon-fire_fire",
      "target": "icon-discount_discount",
      "relation": "conceptually_related_to",
      "confidence": "INFERRED",
      "confidence_score": 0.75,
      "source_file": "assets/icon-fire.svg",
      "source_location": null,
      "weight": 0.75
    },
    {
      "source": "icon-pants_apparel",
      "target": "icon-shirt_apparel",
      "relation": "semantically_similar_to",
      "confidence": "EXTRACTED",
      "confidence_score": 1.0,
      "source_file": "assets/icon-pants.svg",
      "source_location": null,
      "weight": 1.0
    },
    {
      "source": "icon-play_media",
      "target": "icon-pause_media",
      "relation": "semantically_similar_to",
      "confidence": "EXTRACTED",
      "confidence_score": 1.0,
      "source_file": "assets/icon-play.svg",
      "source_location": null,
      "weight": 1.0
    },
    {
      "source": "icon-pepper_food",
      "target": "icon-serving-dish_food",
      "relation": "semantically_similar_to",
      "confidence": "INFERRED",
      "confidence_score": 0.85,
      "source_file": "assets/icon-pepper.svg",
      "source_location": null,
      "weight": 0.85
    },
    {
      "source": "icon-pinterest_social",
      "target": "icon-share_social",
      "relation": "semantically_similar_to",
      "confidence": "INFERRED",
      "confidence_score": 0.85,
      "source_file": "assets/icon-pinterest.svg",
      "source_location": null,
      "weight": 0.85
    },
    {
      "source": "icon-plus_ui",
      "target": "icon-remove_ui",
      "relation": "semantically_similar_to",
      "confidence": "INFERRED",
      "confidence_score": 0.95,
      "source_file": "assets/icon-plus.svg",
      "source_location": null,
      "weight": 0.95
    },
    {
      "source": "icon-plus_ui",
      "target": "icon-reset_ui",
      "relation": "semantically_similar_to",
      "confidence": "INFERRED",
      "confidence_score": 0.75,
      "source_file": "assets/icon-plus.svg",
      "source_location": null,
      "weight": 0.75
    },
    {
      "source": "icon-padlock_security",
      "target": "icon-price-tag_ecommerce",
      "relation": "conceptually_related_to",
      "confidence": "INFERRED",
      "confidence_score": 0.75,
      "source_file": "assets/icon-padlock.svg",
      "source_location": null,
      "weight": 0.75
    },
    {
      "source": "icon-plane_shipping",
      "target": "icon-return_ecommerce",
      "relation": "conceptually_related_to",
      "confidence": "INFERRED",
      "confidence_score": 0.85,
      "source_file": "assets/icon-plane.svg",
      "source_location": null,
      "weight": 0.85
    },
    {
      "source": "icon-recycle_sustainability",
      "target": "icon-plant_nature",
      "relation": "conceptually_related_to",
      "confidence": "INFERRED",
      "confidence_score": 0.75,
      "source_file": "assets/icon-recycle.svg",
      "source_location": null,
      "weight": 0.75
    },
    {
      "source": "icon-ruler_sizing",
      "target": "icon-pants_apparel",
      "relation": "conceptually_related_to",
      "confidence": "INFERRED",
      "confidence_score": 0.85,
      "source_file": "assets/icon-ruler.svg",
      "source_location": null,
      "weight": 0.85
    },
    {
      "source": "icon-ruler_sizing",
      "target": "icon-shirt_apparel",
      "relation": "conceptually_related_to",
      "confidence": "INFERRED",
      "confidence_score": 0.85,
      "source_file": "assets/icon-ruler.svg",
      "source_location": null,
      "weight": 0.85
    },
    {
      "source": "icon-question-mark_ui",
      "target": "icon-padlock_security",
      "relation": "conceptually_related_to",
      "confidence": "INFERRED",
      "confidence_score": 0.55,
      "source_file": "assets/icon-question-mark.svg",
      "source_location": null,
      "weight": 0.55
    },
    {
      "source": "icon-paw-print_pet",
      "target": "icon-plant_nature",
      "relation": "conceptually_related_to",
      "confidence": "INFERRED",
      "confidence_score": 0.65,
      "source_file": "assets/icon-paw-print.svg",
      "source_location": null,
      "weight": 0.65
    },
    {
      "source": "icon-perfume_beauty",
      "target": "icon-price-tag_ecommerce",
      "relation": "conceptually_related_to",
      "confidence": "INFERRED",
      "confidence_score": 0.75,
      "source_file": "assets/icon-perfume.svg",
      "source_location": null,
      "weight": 0.75
    },
    {
      "source": "icon-search_ui",
      "target": "icon-question-mark_ui",
      "relation": "semantically_similar_to",
      "confidence": "INFERRED",
      "confidence_score": 0.65,
      "source_file": "assets/icon-search.svg",
      "source_location": null,
      "weight": 0.65
    },
    {
      "source": "icon-remove_ui",
      "target": "icon-reset_ui",
      "relation": "semantically_similar_to",
      "confidence": "INFERRED",
      "confidence_score": 0.75,
      "source_file": "assets/icon-remove.svg",
      "source_location": null,
      "weight": 0.75
    },
    {
      "source": "icon-plant_nature",
      "target": "icon-pepper_food",
      "relation": "conceptually_related_to",
      "confidence": "INFERRED",
      "confidence_score": 0.65,
      "source_file": "assets/icon-plant.svg",
      "source_location": null,
      "weight": 0.65
    },
    {
      "source": "icon-serving-dish_food",
      "target": "icon-price-tag_ecommerce",
      "relation": "conceptually_related_to",
      "confidence": "INFERRED",
      "confidence_score": 0.65,
      "source_file": "assets/icon-serving-dish.svg",
      "source_location": null,
      "weight": 0.65
    },
    {
      "source": "icon_snapchat",
      "target": "category_social_media_icons",
      "relation": "conceptually_related_to",
      "confidence": "INFERRED",
      "confidence_score": 0.95,
      "source_file": "assets/icon-snapchat.svg",
      "source_location": null,
      "weight": 1.0
    },
    {
      "source": "icon_tiktok",
      "target": "category_social_media_icons",
      "relation": "conceptually_related_to",
      "confidence": "INFERRED",
      "confidence_score": 0.95,
      "source_file": "assets/icon-tiktok.svg",
      "source_location": null,
      "weight": 1.0
    },
    {
      "source": "icon_tumblr",
      "target": "category_social_media_icons",
      "relation": "conceptually_related_to",
      "confidence": "INFERRED",
      "confidence_score": 0.95,
      "source_file": "assets/icon-tumblr.svg",
      "source_location": null,
      "weight": 1.0
    },
    {
      "source": "icon_twitter",
      "target": "category_social_media_icons",
      "relation": "conceptually_related_to",
      "confidence": "INFERRED",
      "confidence_score": 0.95,
      "source_file": "assets/icon-twitter.svg",
      "source_location": null,
      "weight": 1.0
    },
    {
      "source": "icon_vimeo",
      "target": "category_social_media_icons",
      "relation": "conceptually_related_to",
      "confidence": "INFERRED",
      "confidence_score": 0.95,
      "source_file": "assets/icon-vimeo.svg",
      "source_location": null,
      "weight": 1.0
    },
    {
      "source": "icon_youtube",
      "target": "category_social_media_icons",
      "relation": "conceptually_related_to",
      "confidence": "INFERRED",
      "confidence_score": 0.95,
      "source_file": "assets/icon-youtube.svg",
      "source_location": null,
      "weight": 1.0
    },
    {
      "source": "icon_success",
      "target": "category_ui_feedback_icons",
      "relation": "conceptually_related_to",
      "confidence": "INFERRED",
      "confidence_score": 0.95,
      "source_file": "assets/icon-success.svg",
      "source_location": null,
      "weight": 1.0
    },
    {
      "source": "icon_tick",
      "target": "category_ui_feedback_icons",
      "relation": "conceptually_related_to",
      "confidence": "INFERRED",
      "confidence_score": 0.95,
      "source_file": "assets/icon-tick.svg",
      "source_location": null,
      "weight": 1.0
    },
    {
      "source": "icon_unavailable",
      "target": "category_ui_feedback_icons",
      "relation": "conceptually_related_to",
      "confidence": "INFERRED",
      "confidence_score": 0.95,
      "source_file": "assets/icon-unavailable.svg",
      "source_location": null,
      "weight": 1.0
    },
    {
      "source": "icon_star",
      "target": "category_ui_feedback_icons",
      "relation": "conceptually_related_to",
      "confidence": "INFERRED",
      "confidence_score": 0.85,
      "source_file": "assets/icon-star.svg",
      "source_location": null,
      "weight": 1.0
    },
    {
      "source": "loading_spinner",
      "target": "category_ui_feedback_icons",
      "relation": "conceptually_related_to",
      "confidence": "INFERRED",
      "confidence_score": 0.95,
      "source_file": "assets/loading-spinner.svg",
      "source_location": null,
      "weight": 1.0
    },
    {
      "source": "icon_success",
      "target": "icon_tick",
      "relation": "semantically_similar_to",
      "confidence": "INFERRED",
      "confidence_score": 0.85,
      "source_file": "assets/icon-success.svg",
      "source_location": null,
      "weight": 1.0
    },
    {
      "source": "icon_unavailable",
      "target": "icon_success",
      "relation": "conceptually_related_to",
      "confidence": "INFERRED",
      "confidence_score": 0.85,
      "source_file": "assets/icon-unavailable.svg",
      "source_location": null,
      "weight": 1.0
    },
    {
      "source": "icon_truck",
      "target": "category_ecommerce_icons",
      "relation": "conceptually_related_to",
      "confidence": "INFERRED",
      "confidence_score": 0.95,
      "source_file": "assets/icon-truck.svg",
      "source_location": null,
      "weight": 1.0
    },
    {
      "source": "icon_shoe",
      "target": "category_ecommerce_icons",
      "relation": "conceptually_related_to",
      "confidence": "INFERRED",
      "confidence_score": 0.85,
      "source_file": "assets/icon-shoe.svg",
      "source_location": null,
      "weight": 1.0
    },
    {
      "source": "icon_silhouette",
      "target": "category_ecommerce_icons",
      "relation": "conceptually_related_to",
      "confidence": "INFERRED",
      "confidence_score": 0.85,
      "source_file": "assets/icon-silhouette.svg",
      "source_location": null,
      "weight": 1.0
    },
    {
      "source": "icon_zoom",
      "target": "category_ecommerce_icons",
      "relation": "conceptually_related_to",
      "confidence": "INFERRED",
      "confidence_score": 0.85,
      "source_file": "assets/icon-zoom.svg",
      "source_location": null,
      "weight": 1.0
    },
    {
      "source": "icon_star",
      "target": "category_ecommerce_icons",
      "relation": "conceptually_related_to",
      "confidence": "INFERRED",
      "confidence_score": 0.85,
      "source_file": "assets/icon-star.svg",
      "source_location": null,
      "weight": 1.0
    },
    {
      "source": "icon_stopwatch",
      "target": "category_ecommerce_icons",
      "relation": "conceptually_related_to",
      "confidence": "INFERRED",
      "confidence_score": 0.75,
      "source_file": "assets/icon-stopwatch.svg",
      "source_location": null,
      "weight": 1.0
    },
    {
      "source": "icon_washing",
      "target": "category_product_care_icons",
      "relation": "conceptually_related_to",
      "confidence": "INFERRED",
      "confidence_score": 0.95,
      "source_file": "assets/icon-washing.svg",
      "source_location": null,
      "weight": 1.0
    },
    {
      "source": "icon_snowflake",
      "target": "category_product_care_icons",
      "relation": "conceptually_related_to",
      "confidence": "INFERRED",
      "confidence_score": 0.85,
      "source_file": "assets/icon-snowflake.svg",
      "source_location": null,
      "weight": 1.0
    },
    {
      "source": "icon_washing",
      "target": "icon_snowflake",
      "relation": "semantically_similar_to",
      "confidence": "INFERRED",
      "confidence_score": 0.75,
      "source_file": "assets/icon-washing.svg",
      "source_location": null,
      "weight": 1.0
    },
    {
      "source": "mask_arch",
      "target": "category_ui_shapes",
      "relation": "conceptually_related_to",
      "confidence": "INFERRED",
      "confidence_score": 0.95,
      "source_file": "assets/mask-arch.svg",
      "source_location": null,
      "weight": 1.0
    },
    {
      "source": "square",
      "target": "category_ui_shapes",
      "relation": "conceptually_related_to",
      "confidence": "INFERRED",
      "confidence_score": 0.95,
      "source_file": "assets/square.svg",
      "source_location": null,
      "weight": 1.0
    },
    {
      "source": "sparkle_gif",
      "target": "category_ui_shapes",
      "relation": "conceptually_related_to",
      "confidence": "INFERRED",
      "confidence_score": 0.75,
      "source_file": "assets/sparkle.gif",
      "source_location": null,
      "weight": 1.0
    },
    {
      "source": "icon_shopify",
      "target": "category_platform_branding",
      "relation": "conceptually_related_to",
      "confidence": "EXTRACTED",
      "confidence_score": 1.0,
      "source_file": "assets/icon-shopify.svg",
      "source_location": null,
      "weight": 1.0
    },
    {
      "source": "icon_zoom",
      "target": "category_ui_shapes",
      "relation": "conceptually_related_to",
      "confidence": "INFERRED",
      "confidence_score": 0.75,
      "source_file": "assets/icon-zoom.svg",
      "source_location": null,
      "weight": 1.0
    },
    {
      "source": "mask_arch",
      "target": "icon_shoe",
      "relation": "conceptually_related_to",
      "confidence": "AMBIGUOUS",
      "confidence_score": 0.2,
      "source_file": "assets/mask-arch.svg",
      "source_location": null,
      "weight": 1.0
    },
    {
      "source": "icon_shopify",
      "target": "category_ecommerce_icons",
      "relation": "conceptually_related_to",
      "confidence": "INFERRED",
      "confidence_score": 0.95,
      "source_file": "assets/icon-shopify.svg",
      "source_location": null,
      "weight": 1.0
    },
    {
      "source": "loading_spinner",
      "target": "category_ui_shapes",
      "relation": "conceptually_related_to",
      "confidence": "INFERRED",
      "confidence_score": 0.85,
      "source_file": "assets/loading-spinner.svg",
      "source_location": null,
      "weight": 1.0
    }
  ],
  "hyperedges": [
    {
      "id": "ci_quality_pipeline",
      "label": "CI Quality Pipeline: GitHub Actions, Lighthouse CI, Theme Check Action",
      "nodes": [
        "readme_github_actions",
        "readme_lighthouse_ci_action",
        "readme_theme_check_action"
      ],
      "relation": "implement",
      "confidence": "EXTRACTED",
      "confidence_score": 1.0,
      "source_file": "README.md"
    },
    {
      "id": "dawn_design_principles",
      "label": "Dawn Core Design Principles: HTML-First, Progressive Enhancement, Server-Rendered",
      "nodes": [
        "readme_html_first_approach",
        "readme_progressive_enhancement",
        "readme_server_rendered"
      ],
      "relation": "form",
      "confidence": "EXTRACTED",
      "confidence_score": 1.0,
      "source_file": "README.md"
    },
    {
      "id": "translation_ownership",
      "label": "Translation Ownership: Buyer Component, Merchant Component, Themes Translations Team",
      "nodes": [
        "translation_buyer_component",
        "translation_merchant_component",
        "translation_themes_translations_team"
      ],
      "relation": "participate_in",
      "confidence": "EXTRACTED",
      "confidence_score": 1.0,
      "source_file": "translation.yml"
    },
    {
      "id": "group_email_signup_banner_backgrounds",
      "label": "Email Signup Banner Backgrounds",
      "nodes": [
        "email_signup_banner_background_mobile_bg",
        "email_signup_banner_background_bg"
      ],
      "relation": "implement",
      "confidence": "EXTRACTED",
      "confidence_score": 1.0,
      "source_file": "assets/email-signup-banner-background.svg"
    },
    {
      "id": "group_food_icons",
      "label": "Food & Ingredient Icons (Supplement Flavor/Ingredient Indicators)",
      "nodes": [
        "icon_apple_icon",
        "icon_banana_icon",
        "icon_carrot_icon"
      ],
      "relation": "participate_in",
      "confidence": "INFERRED",
      "confidence_score": 0.95,
      "source_file": "assets/icon-apple.svg"
    },
    {
      "id": "group_dietary_badge_icons",
      "label": "Dietary & Ingredient Badge Icons",
      "nodes": [
        "icon_dairy_icon",
        "icon_dairy_free_icon"
      ],
      "relation": "participate_in",
      "confidence": "INFERRED",
      "confidence_score": 0.95,
      "source_file": "assets/icon-dairy.svg"
    },
    {
      "id": "group_product_container_icons",
      "label": "Product Container Icons (Supplement Packaging)",
      "nodes": [
        "icon_bottle_icon",
        "icon_box_icon"
      ],
      "relation": "participate_in",
      "confidence": "INFERRED",
      "confidence_score": 0.85,
      "source_file": "assets/icon-bottle.svg"
    },
    {
      "id": "group_ui_navigation_icons",
      "label": "UI Navigation Icons",
      "nodes": [
        "icon_arrow_icon",
        "icon_caret_icon"
      ],
      "relation": "participate_in",
      "confidence": "INFERRED",
      "confidence_score": 0.95,
      "source_file": "assets/icon-arrow.svg"
    },
    {
      "id": "group_ui_dismiss_icons",
      "label": "UI Dismiss / Close Icons",
      "nodes": [
        "icon_close_icon",
        "icon_close_small_icon"
      ],
      "relation": "participate_in",
      "confidence": "INFERRED",
      "confidence_score": 0.95,
      "source_file": "assets/icon-close.svg"
    },
    {
      "id": "group_ui_confirmation_icons",
      "label": "UI Confirmation / Success Icons",
      "nodes": [
        "icon_check_mark_icon",
        "icon_checkmark_icon"
      ],
      "relation": "participate_in",
      "confidence": "INFERRED",
      "confidence_score": 0.95,
      "source_file": "assets/icon-check-mark.svg"
    },
    {
      "id": "group_ui_copy_paste_icons",
      "label": "UI Copy / Clipboard Icons",
      "nodes": [
        "icon_clipboard_icon",
        "icon_copy_icon"
      ],
      "relation": "participate_in",
      "confidence": "INFERRED",
      "confidence_score": 0.85,
      "source_file": "assets/icon-clipboard.svg"
    },
    {
      "id": "group_ecommerce_ui_icons",
      "label": "E-Commerce Core UI Icons",
      "nodes": [
        "icon_account_icon",
        "icon_cart_icon",
        "icon_cart_empty_icon",
        "icon_chat_bubble_icon"
      ],
      "relation": "participate_in",
      "confidence": "INFERRED",
      "confidence_score": 0.95,
      "source_file": "assets/icon-cart.svg"
    },
    {
      "id": "group_accordion_icons",
      "label": "Accordion / Expandable Section Icons",
      "nodes": [
        "icon_apple_icon",
        "icon_banana_icon",
        "icon_bottle_icon",
        "icon_box_icon",
        "icon_carrot_icon",
        "icon_chat_bubble_icon",
        "icon_check_mark_icon",
        "icon_clipboard_icon",
        "icon_dairy_icon",
        "icon_dairy_free_icon"
      ],
      "relation": "implement",
      "confidence": "EXTRACTED",
      "confidence_score": 1.0,
      "source_file": "assets/icon-apple.svg"
    },
    {
      "id": "group_all_chunk02_assets",
      "label": "All Chunk 02 Theme Assets",
      "nodes": [
        "email_signup_banner_background_mobile_bg",
        "email_signup_banner_background_bg",
        "icon_3d_model_icon",
        "icon_account_icon",
        "icon_apple_icon",
        "icon_arrow_icon",
        "icon_banana_icon",
        "icon_bottle_icon",
        "icon_box_icon",
        "icon_caret_icon",
        "icon_carrot_icon",
        "icon_cart_empty_icon",
        "icon_cart_icon",
        "icon_chat_bubble_icon",
        "icon_check_mark_icon",
        "icon_checkmark_icon",
        "icon_clipboard_icon",
        "icon_close_small_icon",
        "icon_close_icon",
        "icon_copy_icon",
        "icon_dairy_free_icon",
        "icon_dairy_icon"
      ],
      "relation": "participate_in",
      "confidence": "EXTRACTED",
      "confidence_score": 1.0,
      "source_file": "assets/email-signup-banner-background.svg"
    },
    {
      "id": "group_dietary_allergen_badges",
      "label": "Dietary and Allergen Claim Badge Icons",
      "nodes": [
        "icon-gluten-free_gluten_free",
        "icon-nut-free_nut_free",
        "icon-leaf_leaf"
      ],
      "relation": "form",
      "confidence": "INFERRED",
      "confidence_score": 0.95,
      "source_file": "assets/icon-gluten-free.svg"
    },
    {
      "id": "group_social_media_share",
      "label": "Social Media Share Icons Group",
      "nodes": [
        "icon-facebook_facebook",
        "icon-instagram_instagram"
      ],
      "relation": "form",
      "confidence": "INFERRED",
      "confidence_score": 0.95,
      "source_file": "assets/icon-facebook.svg"
    },
    {
      "id": "group_ui_status_feedback",
      "label": "UI Status and Feedback Icons Group",
      "nodes": [
        "icon-error_error",
        "icon-info_info",
        "icon-inventory-status_inventory_status"
      ],
      "relation": "form",
      "confidence": "INFERRED",
      "confidence_score": 0.95,
      "source_file": "assets/icon-error.svg"
    },
    {
      "id": "group_laundry_care",
      "label": "Laundry and Material Care Icons Group",
      "nodes": [
        "icon-dryer_dryer",
        "icon-iron_iron",
        "icon-leather_leather"
      ],
      "relation": "form",
      "confidence": "INFERRED",
      "confidence_score": 0.85,
      "source_file": "assets/icon-dryer.svg"
    },
    {
      "id": "group_product_marketing_claims",
      "label": "Product Marketing and Energy Claim Icons",
      "nodes": [
        "icon-fire_fire",
        "icon-lightning-bolt_lightning_bolt",
        "icon-discount_discount",
        "icon-lipstick_lipstick"
      ],
      "relation": "form",
      "confidence": "INFERRED",
      "confidence_score": 0.75,
      "source_file": "assets/icon-fire.svg"
    },
    {
      "id": "group_ecommerce_actions",
      "label": "E-commerce Shopper Action Icons",
      "nodes": [
        "icon-heart_heart",
        "icon-lock_lock",
        "icon-minus_minus",
        "icon-eye_eye",
        "icon-filter_filter",
        "icon-hamburger_hamburger"
      ],
      "relation": "form",
      "confidence": "INFERRED",
      "confidence_score": 0.85,
      "source_file": "assets/icon-heart.svg"
    },
    {
      "id": "group_location_navigation",
      "label": "Location and Navigation Icons",
      "nodes": [
        "icon-map-pin_map_pin",
        "icon-hamburger_hamburger"
      ],
      "relation": "form",
      "confidence": "INFERRED",
      "confidence_score": 0.75,
      "source_file": "assets/icon-map-pin.svg"
    },
    {
      "id": "apparel_icons_group",
      "label": "Apparel / Clothing Icons",
      "nodes": [
        "icon-pants_apparel",
        "icon-shirt_apparel",
        "icon-ruler_sizing"
      ],
      "relation": "form",
      "confidence": "INFERRED",
      "confidence_score": 0.95,
      "source_file": "assets/icon-pants.svg"
    },
    {
      "id": "media_control_icons_group",
      "label": "Media Control Icons",
      "nodes": [
        "icon-play_media",
        "icon-pause_media"
      ],
      "relation": "form",
      "confidence": "EXTRACTED",
      "confidence_score": 1.0,
      "source_file": "assets/icon-play.svg"
    },
    {
      "id": "social_sharing_icons_group",
      "label": "Social Media and Sharing Icons",
      "nodes": [
        "icon-pinterest_social",
        "icon-share_social"
      ],
      "relation": "form",
      "confidence": "EXTRACTED",
      "confidence_score": 1.0,
      "source_file": "assets/icon-pinterest.svg"
    },
    {
      "id": "ui_control_icons_group",
      "label": "UI Control and Action Icons",
      "nodes": [
        "icon-plus_ui",
        "icon-remove_ui",
        "icon-reset_ui",
        "icon-search_ui",
        "icon-question-mark_ui"
      ],
      "relation": "implement",
      "confidence": "INFERRED",
      "confidence_score": 0.95,
      "source_file": "assets/icon-plus.svg"
    },
    {
      "id": "ecommerce_icons_group",
      "label": "Ecommerce and Shopping Icons",
      "nodes": [
        "icon-padlock_security",
        "icon-price-tag_ecommerce",
        "icon-return_ecommerce",
        "icon-plane_shipping"
      ],
      "relation": "implement",
      "confidence": "INFERRED",
      "confidence_score": 0.95,
      "source_file": "assets/icon-price-tag.svg"
    },
    {
      "id": "nature_sustainability_icons_group",
      "label": "Nature and Sustainability Icons",
      "nodes": [
        "icon-plant_nature",
        "icon-recycle_sustainability",
        "icon-paw-print_pet"
      ],
      "relation": "form",
      "confidence": "INFERRED",
      "confidence_score": 0.85,
      "source_file": "assets/icon-plant.svg"
    },
    {
      "id": "food_ingredient_icons_group",
      "label": "Food and Ingredient Icons",
      "nodes": [
        "icon-pepper_food",
        "icon-serving-dish_food"
      ],
      "relation": "form",
      "confidence": "INFERRED",
      "confidence_score": 0.85,
      "source_file": "assets/icon-pepper.svg"
    },
    {
      "id": "beauty_lifestyle_icons_group",
      "label": "Beauty and Lifestyle Product Icons",
      "nodes": [
        "icon-perfume_beauty",
        "icon-paw-print_pet"
      ],
      "relation": "form",
      "confidence": "INFERRED",
      "confidence_score": 0.65,
      "source_file": "assets/icon-perfume.svg"
    },
    {
      "id": "accordion_icon_class_group",
      "label": "Accordion UI Class Icons",
      "nodes": [
        "icon-pants_apparel",
        "icon-paw-print_pet",
        "icon-pepper_food",
        "icon-perfume_beauty",
        "icon-plane_shipping",
        "icon-plant_nature",
        "icon-price-tag_ecommerce",
        "icon-question-mark_ui",
        "icon-recycle_sustainability",
        "icon-return_ecommerce",
        "icon-ruler_sizing",
        "icon-serving-dish_food",
        "icon-shirt_apparel"
      ],
      "relation": "implement",
      "confidence": "EXTRACTED",
      "confidence_score": 1.0,
      "source_file": "assets/icon-pants.svg"
    },
    {
      "id": "social_media_icons_group",
      "label": "Social Media Icons: Snapchat, TikTok, Tumblr, Twitter, Vimeo, YouTube",
      "nodes": [
        "icon_snapchat",
        "icon_tiktok",
        "icon_tumblr",
        "icon_twitter",
        "icon_vimeo",
        "icon_youtube",
        "category_social_media_icons"
      ],
      "relation": "participate_in",
      "confidence": "INFERRED",
      "confidence_score": 0.95,
      "source_file": null
    },
    {
      "id": "ui_feedback_icons_group",
      "label": "UI Feedback Icons: Success, Tick, Unavailable, Star, Loading Spinner",
      "nodes": [
        "icon_success",
        "icon_tick",
        "icon_unavailable",
        "icon_star",
        "loading_spinner",
        "category_ui_feedback_icons"
      ],
      "relation": "participate_in",
      "confidence": "INFERRED",
      "confidence_score": 0.95,
      "source_file": null
    },
    {
      "id": "ecommerce_icons_group",
      "label": "E-Commerce Icons: Shoe, Shopify, Silhouette, Truck, Zoom, Star, Stopwatch",
      "nodes": [
        "icon_shoe",
        "icon_shopify",
        "icon_silhouette",
        "icon_truck",
        "icon_zoom",
        "icon_star",
        "icon_stopwatch",
        "category_ecommerce_icons"
      ],
      "relation": "participate_in",
      "confidence": "INFERRED",
      "confidence_score": 0.85,
      "source_file": null
    },
    {
      "id": "product_care_icons_group",
      "label": "Product Care Icons: Washing, Snowflake",
      "nodes": [
        "icon_washing",
        "icon_snowflake",
        "category_product_care_icons"
      ],
      "relation": "participate_in",
      "confidence": "INFERRED",
      "confidence_score": 0.85,
      "source_file": null
    },
    {
      "id": "ui_shapes_group",
      "label": "UI Shapes / Structural Elements: Mask Arch, Square, Sparkle GIF, Loading Spinner, Zoom",
      "nodes": [
        "mask_arch",
        "square",
        "sparkle_gif",
        "loading_spinner",
        "icon_zoom",
        "category_ui_shapes"
      ],
      "relation": "form",
      "confidence": "INFERRED",
      "confidence_score": 0.85,
      "source_file": null
    },
    {
      "id": "platform_branding_group",
      "label": "Platform Branding: Shopify Logo",
      "nodes": [
        "icon_shopify",
        "category_platform_branding"
      ],
      "relation": "implement",
      "confidence": "EXTRACTED",
      "confidence_score": 1.0,
      "source_file": "assets/icon-shopify.svg"
    }
  ],
  "input_tokens": 1850,
  "output_tokens": 980
}